CHANGELOG
LICENSE
MANIFEST.in
README.rst
setup.py
careers/__init__.py
careers/admin.py
careers/defaults.py
careers/forms.py
careers/models.py
careers/urls.py
careers/views.py
careers/templates/admin/includes/quick_jobpost.html
careers/templates/careers/jobpost_detail.html
careers/templates/careers/jobpost_list.html
careers/templates/careers/includes/filter_panel.html
careers/templatetags/__init__.py
careers/templatetags/career_tags.py
mezzanine_careers.egg-info/PKG-INFO
mezzanine_careers.egg-info/SOURCES.txt
mezzanine_careers.egg-info/dependency_links.txt
mezzanine_careers.egg-info/not-zip-safe
mezzanine_careers.egg-info/requires.txt
mezzanine_careers.egg-info/top_level.txt