Metadata-Version: 1.0
Name: mezzanine-careers
Version: 0.1
Summary: Job Posting application for the Mezzanine CMS
Home-page: https://github.com/mogga/mezzanine-careers
Author: Robert Moggach
Author-email: rob@dashing.tv
License: BSD
Keywords: django,mezzanine,careers
Platform: UNKNOWN
Classifier: Development Status :: 3 - Alpha
Classifier: Environment :: Web Environment
Classifier: Framework :: Django
Classifier: Intended Audience :: Developers
Classifier: License :: OSI Approved :: BSD License
Classifier: Operating System :: OS Independent
Classifier: Programming Language :: Python
Classifier: Topic :: Internet :: WWW/HTTP
Classifier: Topic :: Internet :: WWW/HTTP :: Dynamic Content
Classifier: Topic :: Internet :: WWW/HTTP :: WSGI
Classifier: Topic :: Software Development :: Libraries :: Application Frameworks
Classifier: Topic :: Software Development :: Libraries :: Python Modules
